{ "category": "virtue", "entries": [
  { "term": "repent", "forms": ["repent", "repented", "repenting", "repentance"], "weight": 3 },
  { "term": "pray", "forms": ["prayed", "praying", "prayers"], "weight": 2 },
  { "term": "charity", "forms": ["alms", "almsgiving", "charitably"], "weight": 3 },
  { "term": "give", "forms": ["bestowed", "succoured", "succored"], "weight": 1 },
  { "term": "forgive", "forms": ["forgive", "forgave", "forgiven", "forgiveness", "pardoned"], "weight": 2 },
  { "term": "labour", "forms": ["laboured", "labored", "toiled"], "weight": 2 },
  { "term": "confess", "forms": ["confessed", "confession", "acknowledged"], "weight": 2 },
  { "term": "amend", "forms": ["amend", "amended", "amendment", "reformed", "reformation"], "weight": 2 },
  { "term": "restore", "forms": ["restored", "restitution", "repaid", "repay"], "weight": 2 },
  { "term": "protect", "forms": ["protected", "defended", "rescued", "preserved"], "weight": 1 },
  { "term": "relieve", "forms": ["comforted", "consoled", "nursed", "tended"], "weight": 1 },
  { "term": "thank", "forms": ["thanked"], "weight": 1 }
] }
